adamw_bf16/__init__.py
adamw_bf16/stochastic/__init__.py
adamw_bf16-0.0.3.dist-info/LICENSE.txt
adamw_bf16-0.0.3.dist-info/METADATA
adamw_bf16-0.0.3.dist-info/WHEEL
adamw_bf16-0.0.3.dist-info/top_level.txt
adamw_bf16-0.0.3.dist-info/RECORD
