Metadata-Version: 2.1
Name: adamw_bf16
Version: 0.0.3
Summary: AdamW Optimizer for bfloat16
Author-email: APJC <apjc@usa.com>
Project-URL: Homepage, https://github.com/AmericanPresidentJimmyCarter/adamw-bf16
Project-URL: Issues, https://github.com/AmericanPresidentJimmyCarter/adamw-bf16/issues
Classifier: Programming Language :: Python :: 3
Classifier: License :: OSI Approved :: GNU Affero General Public License v3
Classifier: Operating System :: OS Independent
Requires-Python: >=3.9
License-File: LICENSE.txt
Requires-Dist: torch >=2.1.0
